realswift/__init__.py
realswift/actions.py
realswift/browser_utils.py
realswift/config_module.py
realswift/exceptions.py
realswift/image_utils.py
realswift/internal.py
realswift/main.py
realswift/ocr_utils.py
realswift/reporter.py
realswift-3.0.4.dist-info/LICENSE
realswift-3.0.4.dist-info/METADATA
realswift-3.0.4.dist-info/WHEEL
realswift-3.0.4.dist-info/top_level.txt
realswift-3.0.4.dist-info/RECORD
